SentinelLogAnalyzer/__init__.py
SentinelLogAnalyzer/log_analysis.py
tests/__init__.py
tests/test_SentinelLogAnalyzer.py
SentinelLogAnalyzer-1.0.1.dist-info/LICENSE
SentinelLogAnalyzer-1.0.1.dist-info/METADATA
SentinelLogAnalyzer-1.0.1.dist-info/WHEEL
SentinelLogAnalyzer-1.0.1.dist-info/entry_points.txt
SentinelLogAnalyzer-1.0.1.dist-info/top_level.txt
SentinelLogAnalyzer-1.0.1.dist-info/RECORD
