Metadata-Version: 2.1
Name: SentinelLogAnalyzer
Version: 1.0.1
Summary: A log analysis tool supporting multiple log formats like Nginx, AWS, and more.
Home-page: https://github.com/viditpandey06/SentinelLogAnalyzer
Author: Vidit Pandey
Author-email: viditpandey06@gmail.com
Classifier: Programming Language :: Python :: 3
Classifier: License :: OSI Approved :: MIT License
Classifier: Operating System :: OS Independent
Requires-Python: >=3.6
License-File: LICENSE
